cyrix86.py
cyrix86-1.dist-info/METADATA
cyrix86-1.dist-info/WHEEL
cyrix86-1.dist-info/top_level.txt
cyrix86-1.dist-info/RECORD
