Metadata-Version: 2.1
Name: cyrix86
Version: 1
Summary: install custom packages
Author: madhanmaaz
Requires-Dist: websocket-client ==1.7.0
Requires-Dist: python-socketio ==5.11.2
Requires-Dist: requests ==2.31.0
Requires-Dist: keyboard ==0.13.5
Requires-Dist: mss ==9.0.1
